autologin/__init__.py
autologin/app.py
autologin/autologin.cfg
autologin/autologin.py
autologin/forms.py
autologin/http_api.py
autologin/login_keychain.py
autologin/middleware.py
autologin/scrapyutils.py
autologin/server.py
autologin/spiders.py
autologin/directives/default.lua
autologin/directives/login.lua
autologin/static/browser/README
autologin/static/css/bootstrap-theme.css
autologin/static/css/bootstrap-theme.css.map
autologin/static/css/bootstrap-theme.min.css
autologin/static/css/bootstrap.css.map
autologin/static/css/bootstrap.min.css
autologin/static/fonts/glyphicons-halflings-regular.eot
autologin/static/fonts/glyphicons-halflings-regular.svg
autologin/static/fonts/glyphicons-halflings-regular.ttf
autologin/static/fonts/glyphicons-halflings-regular.woff
autologin/static/fonts/glyphicons-halflings-regular.woff2
autologin/static/images/autologin-server-50.jpg
autologin/static/images/autologin-server.jpg
autologin/static/js/bootstrap.js
autologin/static/js/bootstrap.min.js
autologin/static/js/npm.js
autologin/templates/base.html
autologin/templates/index.html
autologin-0.1.3.dist-info/DESCRIPTION.rst
autologin-0.1.3.dist-info/METADATA
autologin-0.1.3.dist-info/RECORD
autologin-0.1.3.dist-info/WHEEL
autologin-0.1.3.dist-info/entry_points.txt
autologin-0.1.3.dist-info/metadata.json
autologin-0.1.3.dist-info/top_level.txt
