Metadata-Version: 2.0
Name: autologin
Version: 0.1.3
Summary: A utility for finding login links, forms and autologging into websites with a set of valid credentials.
Home-page: https://github.com/TeamHG-Memex/autologin
Author: Alejandro Caceres, Luke Maxwell
Author-email: lukemaxwellshouse@gmail.com
License: MIT
Keywords: login,automated,spider
Platform: UNKNOWN
Classifier: Development Status :: 3 - Alpha
Classifier: Topic :: Internet :: WWW/HTTP :: Indexing/Search
Classifier: License :: OSI Approved :: MIT License
Classifier: Programming Language :: Python
Classifier: Programming Language :: Python :: 2
Classifier: Programming Language :: Python :: 2.7
Classifier: Programming Language :: Python :: 3
Classifier: Programming Language :: Python :: 3.3
Classifier: Programming Language :: Python :: 3.4
Classifier: Programming Language :: Python :: 3.5
Requires-Dist: Flask (==0.10.1)
Requires-Dist: Flask-Admin (==1.4.0)
Requires-Dist: Flask-SQLAlchemy (==2.1)
Requires-Dist: Flask-WTF (==0.12)
Requires-Dist: WTForms (==2.1)
Requires-Dist: crochet
Requires-Dist: formasaurus[with_deps] (>=0.8)
Requires-Dist: lxml
Requires-Dist: numpy
Requires-Dist: requests
Requires-Dist: scikit-learn
Requires-Dist: scipy
Requires-Dist: scrapy (>=1.1.0)
Requires-Dist: scrapy-splash (>=0.4)
Requires-Dist: six
